transformer_lens/ActivationCache.py
transformer_lens/BertNextSentencePrediction.py
transformer_lens/FactoredMatrix.py
transformer_lens/HookedEncoder.py
transformer_lens/HookedEncoderDecoder.py
transformer_lens/HookedTransformer.py
transformer_lens/HookedTransformerConfig.py
transformer_lens/SVDInterpreter.py
transformer_lens/__init__.py
transformer_lens/components/__init__.py
transformer_lens/components/abstract_attention.py
transformer_lens/components/attention.py
transformer_lens/components/bert_block.py
transformer_lens/components/bert_embed.py
transformer_lens/components/bert_mlm_head.py
transformer_lens/components/bert_nsp_head.py
transformer_lens/components/bert_pooler.py
transformer_lens/components/embed.py
transformer_lens/components/grouped_query_attention.py
transformer_lens/components/layer_norm.py
transformer_lens/components/layer_norm_pre.py
transformer_lens/components/mlps/can_be_used_as_mlp.py
transformer_lens/components/mlps/gated_mlp.py
transformer_lens/components/mlps/gated_mlp_4bit.py
transformer_lens/components/mlps/mlp.py
transformer_lens/components/mlps/moe.py
transformer_lens/components/pos_embed.py
transformer_lens/components/rms_norm.py
transformer_lens/components/rms_norm_pre.py
transformer_lens/components/t5_attention.py
transformer_lens/components/t5_block.py
transformer_lens/components/token_typed_embed.py
transformer_lens/components/transformer_block.py
transformer_lens/components/unembed.py
transformer_lens/evals.py
transformer_lens/factories/activation_function_factory.py
transformer_lens/factories/mlp_factory.py
transformer_lens/head_detector.py
transformer_lens/hook_points.py
transformer_lens/loading_from_pretrained.py
transformer_lens/past_key_value_caching.py
transformer_lens/patching.py
transformer_lens/pretrained/__init__.py
transformer_lens/pretrained/weight_conversions/__init__.py
transformer_lens/pretrained/weight_conversions/bert.py
transformer_lens/pretrained/weight_conversions/bloom.py
transformer_lens-2.16.1.dist-info/LICENSE
transformer_lens-2.16.1.dist-info/METADATA
transformer_lens-2.16.1.dist-info/WHEEL
transformer_lens-2.16.1.dist-info/entry_points.txt
transformer_lens-2.16.1.dist-info/RECORD
