Metadata-Version: 2.3
Name: transformer-lens
Version: 2.16.1
Summary: An implementation of transformers tailored for mechanistic interpretability.
License: MIT
Author: Neel Nanda
Author-email: 77788841+TransformerLensOrg@users.noreply.github.com
Requires-Python: >=3.8,<4.0
Classifier: License :: OSI Approved :: MIT License
Classifier: Programming Language :: Python :: 3
Classifier: Programming Language :: Python :: 3.8
Classifier: Programming Language :: Python :: 3.9
Classifier: Programming Language :: Python :: 3.10
Classifier: Programming Language :: Python :: 3.11
Classifier: Programming Language :: Python :: 3.12
Classifier: Programming Language :: Python :: 3.13
Requires-Dist: accelerate (>=0.23.0)
Requires-Dist: beartype (>=0.14.1,<0.15.0)
Requires-Dist: better-abc (>=0.0.3,<0.0.4)
Requires-Dist: datasets (>=2.7.1)
Requires-Dist: einops (>=0.6.0)
Requires-Dist: fancy-einsum (>=0.0.3)
Requires-Dist: jaxtyping (>=0.2.11)
Requires-Dist: numpy (>=1.20,<1.25) ; python_version == "3.8"
Requires-Dist: numpy (>=1.24,<2) ; python_version >= "3.9" and python_version < "3.12"
Requires-Dist: numpy (>=1.26,<2) ; python_version == "3.12"
Requires-Dist: pandas (>=1.1.5)
Requires-Dist: rich (>=12.6.0)
Requires-Dist: sentencepiece
Requires-Dist: torch (<2.6) ; python_version == "3.8"
Requires-Dist: torch (>=2.6) ; python_version >= "3.9"
Requires-Dist: tqdm (>=4.64.1)
Requires-Dist: transformers (<4.51) ; python_version == "3.8"
Requires-Dist: transformers (>=4.51) ; python_version >= "3.9"
Requires-Dist: transformers-stream-generator (>=0.0.5,<0.0.6)
Requires-Dist: typeguard (>=4.2,<5.0)
Requires-Dist: typing-extensions
Requires-Dist: wandb (>=0.13.5)
